<com.tongji.hbase.migration.Adapter>
  <tableDefs>
    <entry>
      <string>Picture</string>
      <com.tongji.hbase.migration.common.TableDef>
        <tableName>Picture</tableName>
        <columnKeys>
          <entry>
            <string>pictureType</string>
            <string>VARCHAR(50)</string>
          </entry>
          <entry>
            <string>pictureSrc</string>
            <string>VARCHAR(50)</string>
          </entry>
          <entry>
            <string>picCreator</string>
            <string>VARCHAR(50)</string>
          </entry>
          <entry>
            <string>picCreateDate</string>
            <string>DATETIME</string>
          </entry>
          <entry>
            <string>typeID</string>
            <string>INT</string>
          </entry>
          <entry>
            <string>pictureID</string>
            <string>INT</string>
          </entry>
        </columnKeys>
        <primaryKeys>
          <string>pictureID</string>
        </primaryKeys>
        <hasOneRefTables>
          <entry>
            <string>Type</string>
            <string>typeID</string>
          </entry>
        </hasOneRefTables>
        <hasManyRefTables/>
      </com.tongji.hbase.migration.common.TableDef>
    </entry>
    <entry>
      <string>Collection</string>
      <com.tongji.hbase.migration.common.TableDef>
        <tableName>Collection</tableName>
        <columnKeys>
          <entry>
            <string>typeName</string>
            <string>VARCHAR(50)</string>
          </entry>
          <entry>
            <string>userID</string>
            <string>BIGINT</string>
          </entry>
          <entry>
            <string>collectionID</string>
            <string>BIGINT</string>
          </entry>
          <entry>
            <string>goodsIDS</string>
            <string>TEXT</string>
          </entry>
          <entry>
            <string>type</string>
            <string>VARCHAR(50)</string>
          </entry>
        </columnKeys>
        <primaryKeys>
          <string>collectionID</string>
        </primaryKeys>
        <hasOneRefTables/>
        <hasManyRefTables>
          <entry>
            <string>Goods</string>
            <string>goodsIDS</string>
          </entry>
        </hasManyRefTables>
      </com.tongji.hbase.migration.common.TableDef>
    </entry>
    <entry>
      <string>Brand</string>
      <com.tongji.hbase.migration.common.TableDef>
        <tableName>Brand</tableName>
        <columnKeys>
          <entry>
            <string>brandID</string>
            <string>INT</string>
          </entry>
          <entry>
            <string>brandOrder</string>
            <string>INT</string>
          </entry>
          <entry>
            <string>brandCreator</string>
            <string>VARCHAR(50)</string>
          </entry>
          <entry>
            <string>brandEnglishName</string>
            <string>VARCHAR(50)</string>
          </entry>
          <entry>
            <string>brandCreateDate</string>
            <string>DATETIME</string>
          </entry>
          <entry>
            <string>brandDesc</string>
            <string>VARCHAR(100)</string>
          </entry>
          <entry>
            <string>brandName</string>
            <string>VARCHAR(50)</string>
          </entry>
          <entry>
            <string>pictureID</string>
            <string>BIGINT</string>
          </entry>
        </columnKeys>
        <primaryKeys>
          <string>brandID</string>
        </primaryKeys>
        <hasOneRefTables>
          <entry>
            <string>Picture</string>
            <string>pictureID</string>
          </entry>
        </hasOneRefTables>
        <hasManyRefTables/>
      </com.tongji.hbase.migration.common.TableDef>
    </entry>
    <entry>
      <string>Model</string>
      <com.tongji.hbase.migration.common.TableDef>
        <tableName>Model</tableName>
        <columnKeys>
          <entry>
            <string>packageWeight</string>
            <string>FLOAT(53)</string>
          </entry>
          <entry>
            <string>modelID</string>
            <string>BIGINT</string>
          </entry>
          <entry>
            <string>height</string>
            <string>FLOAT(53)</string>
          </entry>
          <entry>
            <string>isDefault</string>
            <string>BIT</string>
          </entry>
          <entry>
            <string>modelSrc</string>
            <string>VARCHAR(50)</string>
          </entry>
          <entry>
            <string>width</string>
            <string>FLOAT(53)</string>
          </entry>
          <entry>
            <string>length</string>
            <string>FLOAT(53)</string>
          </entry>
          <entry>
            <string>modelCreator</string>
            <string>VARCHAR(50)</string>
          </entry>
          <entry>
            <string>goodsID</string>
            <string>BIGINT</string>
          </entry>
          <entry>
            <string>modelCreateDate</string>
            <string>DATETIME</string>
          </entry>
          <entry>
            <string>packageSize</string>
            <string>VARCHAR(50)</string>
          </entry>
        </columnKeys>
        <primaryKeys>
          <string>modelID</string>
        </primaryKeys>
        <hasOneRefTables>
          <entry>
            <string>Goods</string>
            <string>goodsID</string>
          </entry>
        </hasOneRefTables>
        <hasManyRefTables/>
      </com.tongji.hbase.migration.common.TableDef>
    </entry>
    <entry>
      <string>Type</string>
      <com.tongji.hbase.migration.common.TableDef>
        <tableName>Type</tableName>
        <columnKeys>
          <entry>
            <string>typeName</string>
            <string>VARCHAR(50)</string>
          </entry>
          <entry>
            <string>parentID</string>
            <string>INT</string>
          </entry>
          <entry>
            <string>tag</string>
            <string>NVARCHAR(50)</string>
          </entry>
          <entry>
            <string>typeLevel</string>
            <string>INT</string>
          </entry>
          <entry>
            <string>typeCreateDate</string>
            <string>DATETIME</string>
          </entry>
          <entry>
            <string>typeCreator</string>
            <string>VARCHAR(50)</string>
          </entry>
          <entry>
            <string>typeID</string>
            <string>INT</string>
          </entry>
        </columnKeys>
        <primaryKeys>
          <string>typeID</string>
        </primaryKeys>
        <hasOneRefTables/>
        <hasManyRefTables/>
      </com.tongji.hbase.migration.common.TableDef>
    </entry>
    <entry>
      <string>GoodsRelated</string>
      <com.tongji.hbase.migration.common.TableDef>
        <tableName>GoodsRelated</tableName>
        <columnKeys>
          <entry>
            <string>colorID</string>
            <string>INT</string>
          </entry>
          <entry>
            <string>modelID</string>
            <string>INT</string>
          </entry>
          <entry>
            <string>goodsRelatedID</string>
            <string>INT</string>
          </entry>
          <entry>
            <string>goodsRelatedCreateDate</string>
            <string>DATETIME</string>
          </entry>
          <entry>
            <string>goodsRelatedCreator</string>
            <string>VARCHAR(50)</string>
          </entry>
          <entry>
            <string>goodsPrice</string>
            <string>FLOAT(53)</string>
          </entry>
          <entry>
            <string>goodsCount</string>
            <string>INT</string>
          </entry>
          <entry>
            <string>pictureID</string>
            <string>BIGINT</string>
          </entry>
        </columnKeys>
        <primaryKeys>
          <string>goodsRelatedID</string>
        </primaryKeys>
        <hasOneRefTables>
          <entry>
            <string>Picture</string>
            <string>pictureID</string>
          </entry>
          <entry>
            <string>Model</string>
            <string>modelID</string>
          </entry>
          <entry>
            <string>Color</string>
            <string>colorID</string>
          </entry>
        </hasOneRefTables>
        <hasManyRefTables/>
      </com.tongji.hbase.migration.common.TableDef>
    </entry>
    <entry>
      <string>House</string>
      <com.tongji.hbase.migration.common.TableDef>
        <tableName>House</tableName>
        <columnKeys>
          <entry>
            <string>houseModelSrc</string>
            <string>TEXT</string>
          </entry>
          <entry>
            <string>houseArea</string>
            <string>FLOAT(53)</string>
          </entry>
          <entry>
            <string>tag</string>
            <string>INT</string>
          </entry>
          <entry>
            <string>houseRemark</string>
            <string>VARCHAR(50)</string>
          </entry>
          <entry>
            <string>cantavilID</string>
            <string>BIGINT</string>
          </entry>
          <entry>
            <string>housePicSrc</string>
            <string>VARCHAR(50)</string>
          </entry>
          <entry>
            <string>houseName</string>
            <string>VARCHAR(50)</string>
          </entry>
          <entry>
            <string>houseCreator</string>
            <string>VARCHAR(50)</string>
          </entry>
          <entry>
            <string>houseTypeID</string>
            <string>BIGINT</string>
          </entry>
          <entry>
            <string>houseFormID</string>
            <string>BIGINT</string>
          </entry>
          <entry>
            <string>houseID</string>
            <string>BIGINT</string>
          </entry>
          <entry>
            <string>houseCreateDate</string>
            <string>DATETIME</string>
          </entry>
          <entry>
            <string>houseStyleIDs</string>
            <string>VARCHAR(50)</string>
          </entry>
          <entry>
            <string>designerID</string>
            <string>BIGINT</string>
          </entry>
        </columnKeys>
        <primaryKeys>
          <string>houseID</string>
        </primaryKeys>
        <hasOneRefTables>
          <entry>
            <string>Cantavil</string>
            <string>cantavilID</string>
          </entry>
        </hasOneRefTables>
        <hasManyRefTables/>
      </com.tongji.hbase.migration.common.TableDef>
    </entry>
    <entry>
      <string>Goods</string>
      <com.tongji.hbase.migration.common.TableDef>
        <tableName>Goods</tableName>
        <columnKeys>
          <entry>
            <string>goodsStyle</string>
            <string>VARCHAR(50)</string>
          </entry>
          <entry>
            <string>goodsCreator</string>
            <string>VARCHAR(50)</string>
          </entry>
          <entry>
            <string>goodsPackage</string>
            <string>VARCHAR(50)</string>
          </entry>
          <entry>
            <string>packageCount</string>
            <string>INT</string>
          </entry>
          <entry>
            <string>goodsLocation</string>
            <string>VARCHAR(50)</string>
          </entry>
          <entry>
            <string>pictureIDs</string>
            <string>TEXT</string>
          </entry>
          <entry>
            <string>goodsMaterial</string>
            <string>VARCHAR(50)</string>
          </entry>
          <entry>
            <string>brandID</string>
            <string>INT</string>
          </entry>
          <entry>
            <string>goodsBill</string>
            <string>SMALLINT</string>
          </entry>
          <entry>
            <string>goodsGuaranteePeriod</string>
            <string>FLOAT(53)</string>
          </entry>
          <entry>
            <string>goodsCreateDate</string>
            <string>DATETIME</string>
          </entry>
          <entry>
            <string>goodsInstallCost</string>
            <string>FLOAT(53)</string>
          </entry>
          <entry>
            <string>goodsID</string>
            <string>INT</string>
          </entry>
          <entry>
            <string>goodsUnit</string>
            <string>VARCHAR(50)</string>
          </entry>
          <entry>
            <string>goodsCityService</string>
            <string>VARCHAR(50)</string>
          </entry>
          <entry>
            <string>goodsName</string>
            <string>VARCHAR(50)</string>
          </entry>
          <entry>
            <string>typeID</string>
            <string>INT</string>
          </entry>
          <entry>
            <string>goodsType</string>
            <string>VARCHAR(50)</string>
          </entry>
        </columnKeys>
        <primaryKeys>
          <string>goodsID</string>
        </primaryKeys>
        <hasOneRefTables>
          <entry>
            <string>Brand</string>
            <string>brandID</string>
          </entry>
          <entry>
            <string>Type</string>
            <string>typeID</string>
          </entry>
        </hasOneRefTables>
        <hasManyRefTables>
          <entry>
            <string>Picture</string>
            <string>pictureIDs</string>
          </entry>
        </hasManyRefTables>
      </com.tongji.hbase.migration.common.TableDef>
    </entry>
    <entry>
      <string>Design</string>
      <com.tongji.hbase.migration.common.TableDef>
        <tableName>Design</tableName>
        <columnKeys>
          <entry>
            <string>isReleased</string>
            <string>BIT</string>
          </entry>
          <entry>
            <string>userID</string>
            <string>BIGINT</string>
          </entry>
          <entry>
            <string>designCreateDate</string>
            <string>DATETIME</string>
          </entry>
          <entry>
            <string>designID</string>
            <string>BIGINT</string>
          </entry>
          <entry>
            <string>designPicSrc</string>
            <string>VARCHAR(50)</string>
          </entry>
          <entry>
            <string>designName</string>
            <string>VARCHAR(50)</string>
          </entry>
          <entry>
            <string>xmlSrc</string>
            <string>TEXT</string>
          </entry>
        </columnKeys>
        <primaryKeys>
          <string>designID</string>
        </primaryKeys>
        <hasOneRefTables/>
        <hasManyRefTables/>
      </com.tongji.hbase.migration.common.TableDef>
    </entry>
    <entry>
      <string>Color</string>
      <com.tongji.hbase.migration.common.TableDef>
        <tableName>Color</tableName>
        <columnKeys>
          <entry>
            <string>colorID</string>
            <string>INT</string>
          </entry>
          <entry>
            <string>colorName</string>
            <string>VARCHAR(50)</string>
          </entry>
          <entry>
            <string>isDefault</string>
            <string>BIT</string>
          </entry>
          <entry>
            <string>colorNum</string>
            <string>VARCHAR(50)</string>
          </entry>
          <entry>
            <string>goodsID</string>
            <string>INT</string>
          </entry>
          <entry>
            <string>colorCreateDate</string>
            <string>DATETIME</string>
          </entry>
          <entry>
            <string>colorCreator</string>
            <string>VARCHAR(50)</string>
          </entry>
        </columnKeys>
        <primaryKeys>
          <string>colorID</string>
        </primaryKeys>
        <hasOneRefTables>
          <entry>
            <string>Goods</string>
            <string>goodsID</string>
          </entry>
        </hasOneRefTables>
        <hasManyRefTables/>
      </com.tongji.hbase.migration.common.TableDef>
    </entry>
    <entry>
      <string>Cantavil</string>
      <com.tongji.hbase.migration.common.TableDef>
        <tableName>Cantavil</tableName>
        <columnKeys>
          <entry>
            <string>cantavilRemark</string>
            <string>VARCHAR(200)</string>
          </entry>
          <entry>
            <string>cantavilAddress</string>
            <string>VARCHAR(50)</string>
          </entry>
          <entry>
            <string>cantavilPic</string>
            <string>VARCHAR(50)</string>
          </entry>
          <entry>
            <string>cantavilDeveloper</string>
            <string>VARCHAR(50)</string>
          </entry>
          <entry>
            <string>cantavilName</string>
            <string>VARCHAR(50)</string>
          </entry>
          <entry>
            <string>cantavilCreateDate</string>
            <string>DATETIME</string>
          </entry>
          <entry>
            <string>cantavilID</string>
            <string>INT</string>
          </entry>
          <entry>
            <string>cantavilCreator</string>
            <string>VARCHAR(50)</string>
          </entry>
          <entry>
            <string>developDesc</string>
            <string>VARCHAR(50)</string>
          </entry>
          <entry>
            <string>cantavilType</string>
            <string>VARCHAR(50)</string>
          </entry>
          <entry>
            <string>typeID</string>
            <string>INT</string>
          </entry>
          <entry>
            <string>pictureID</string>
            <string>INT</string>
          </entry>
        </columnKeys>
        <primaryKeys>
          <string>cantavilID</string>
        </primaryKeys>
        <hasOneRefTables>
          <entry>
            <string>Picture</string>
            <string>pictureID</string>
          </entry>
          <entry>
            <string>Type</string>
            <string>typeID</string>
          </entry>
        </hasOneRefTables>
        <hasManyRefTables/>
      </com.tongji.hbase.migration.common.TableDef>
    </entry>
  </tableDefs>
  <htableDefs>
    <entry>
      <string>Picture</string>
      <com.tongji.hbase.migration.common.HTableDef>
        <tableName>Picture</tableName>
        <rowKey>pictureID</rowKey>
        <columnInfos>
          <entry>
            <string>Picture</string>
            <map>
              <entry>
                <string>pictureSrc</string>
                <com.tongji.hbase.migration.common.HTableDef_-ColumnInfo>
                  <columnName>pictureSrc</columnName>
                  <columnType>STRING</columnType>
                  <refTable>Picture</refTable>
                  <refKey>pictureSrc</refKey>
                  <outer-class reference="../../../../../.."/>
                </com.tongji.hbase.migration.common.HTableDef_-ColumnInfo>
              </entry>
              <entry>
                <string>pictureType</string>
                <com.tongji.hbase.migration.common.HTableDef_-ColumnInfo>
                  <columnName>pictureType</columnName>
                  <columnType>STRING</columnType>
                  <refTable>Picture</refTable>
                  <refKey>pictureType</refKey>
                  <outer-class reference="../../../../../.."/>
                </com.tongji.hbase.migration.common.HTableDef_-ColumnInfo>
              </entry>
              <entry>
                <string>picCreator</string>
                <com.tongji.hbase.migration.common.HTableDef_-ColumnInfo>
                  <columnName>picCreator</columnName>
                  <columnType>STRING</columnType>
                  <refTable>Picture</refTable>
                  <refKey>picCreator</refKey>
                  <outer-class reference="../../../../../.."/>
                </com.tongji.hbase.migration.common.HTableDef_-ColumnInfo>
              </entry>
              <entry>
                <string>picCreateDate</string>
                <com.tongji.hbase.migration.common.HTableDef_-ColumnInfo>
                  <columnName>picCreateDate</columnName>
                  <columnType>DATETIME</columnType>
                  <refTable>Picture</refTable>
                  <refKey>picCreateDate</refKey>
                  <outer-class reference="../../../../../.."/>
                </com.tongji.hbase.migration.common.HTableDef_-ColumnInfo>
              </entry>
              <entry>
                <string>pictureID</string>
                <com.tongji.hbase.migration.common.HTableDef_-ColumnInfo>
                  <columnName>pictureID</columnName>
                  <columnType>INT</columnType>
                  <refTable>Picture</refTable>
                  <refKey>pictureID</refKey>
                  <outer-class reference="../../../../../.."/>
                </com.tongji.hbase.migration.common.HTableDef_-ColumnInfo>
              </entry>
              <entry>
                <string>typeID</string>
                <com.tongji.hbase.migration.common.HTableDef_-ColumnInfo>
                  <columnName>typeID</columnName>
                  <columnType>INT</columnType>
                  <refTable>Picture</refTable>
                  <refKey>typeID</refKey>
                  <outer-class reference="../../../../../.."/>
                </com.tongji.hbase.migration.common.HTableDef_-ColumnInfo>
              </entry>
            </map>
          </entry>
        </columnInfos>
      </com.tongji.hbase.migration.common.HTableDef>
    </entry>
    <entry>
      <string>Brand</string>
      <com.tongji.hbase.migration.common.HTableDef>
        <tableName>Brand</tableName>
        <rowKey>brandID</rowKey>
        <columnInfos>
          <entry>
            <string>Picture</string>
            <map>
              <entry>
                <string>pictureSrc</string>
                <com.tongji.hbase.migration.common.HTableDef_-ColumnInfo>
                  <columnName>pictureSrc</columnName>
                  <columnType>STRING</columnType>
                  <refTable>Picture</refTable>
                  <refKey>pictureSrc</refKey>
                  <outer-class reference="../../../../../.."/>
                </com.tongji.hbase.migration.common.HTableDef_-ColumnInfo>
              </entry>
              <entry>
                <string>pictureType</string>
                <com.tongji.hbase.migration.common.HTableDef_-ColumnInfo>
                  <columnName>pictureType</columnName>
                  <columnType>STRING</columnType>
                  <refTable>Picture</refTable>
                  <refKey>pictureType</refKey>
                  <outer-class reference="../../../../../.."/>
                </com.tongji.hbase.migration.common.HTableDef_-ColumnInfo>
              </entry>
              <entry>
                <string>picCreator</string>
                <com.tongji.hbase.migration.common.HTableDef_-ColumnInfo>
                  <columnName>picCreator</columnName>
                  <columnType>STRING</columnType>
                  <refTable>Picture</refTable>
                  <refKey>picCreator</refKey>
                  <outer-class reference="../../../../../.."/>
                </com.tongji.hbase.migration.common.HTableDef_-ColumnInfo>
              </entry>
              <entry>
                <string>picCreateDate</string>
                <com.tongji.hbase.migration.common.HTableDef_-ColumnInfo>
                  <columnName>picCreateDate</columnName>
                  <columnType>DATETIME</columnType>
                  <refTable>Picture</refTable>
                  <refKey>picCreateDate</refKey>
                  <outer-class reference="../../../../../.."/>
                </com.tongji.hbase.migration.common.HTableDef_-ColumnInfo>
              </entry>
              <entry>
                <string>pictureID</string>
                <com.tongji.hbase.migration.common.HTableDef_-ColumnInfo>
                  <columnName>pictureID</columnName>
                  <columnType>INT</columnType>
                  <refTable>Picture</refTable>
                  <refKey>pictureID</refKey>
                  <outer-class reference="../../../../../.."/>
                </com.tongji.hbase.migration.common.HTableDef_-ColumnInfo>
              </entry>
              <entry>
                <string>typeID</string>
                <com.tongji.hbase.migration.common.HTableDef_-ColumnInfo>
                  <columnName>typeID</columnName>
                  <columnType>INT</columnType>
                  <refTable>Picture</refTable>
                  <refKey>typeID</refKey>
                  <outer-class reference="../../../../../.."/>
                </com.tongji.hbase.migration.common.HTableDef_-ColumnInfo>
              </entry>
            </map>
          </entry>
          <entry>
            <string>Brand</string>
            <map>
              <entry>
                <string>brandID</string>
                <com.tongji.hbase.migration.common.HTableDef_-ColumnInfo>
                  <columnName>brandID</columnName>
                  <columnType>INT</columnType>
                  <refTable>Brand</refTable>
                  <refKey>brandID</refKey>
                  <outer-class reference="../../../../../.."/>
                </com.tongji.hbase.migration.common.HTableDef_-ColumnInfo>
              </entry>
              <entry>
                <string>brandOrder</string>
                <com.tongji.hbase.migration.common.HTableDef_-ColumnInfo>
                  <columnName>brandOrder</columnName>
                  <columnType>INT</columnType>
                  <refTable>Brand</refTable>
                  <refKey>brandOrder</refKey>
                  <outer-class reference="../../../../../.."/>
                </com.tongji.hbase.migration.common.HTableDef_-ColumnInfo>
              </entry>
              <entry>
                <string>brandCreator</string>
                <com.tongji.hbase.migration.common.HTableDef_-ColumnInfo>
                  <columnName>brandCreator</columnName>
                  <columnType>STRING</columnType>
                  <refTable>Brand</refTable>
                  <refKey>brandCreator</refKey>
                  <outer-class reference="../../../../../.."/>
                </com.tongji.hbase.migration.common.HTableDef_-ColumnInfo>
              </entry>
              <entry>
                <string>brandEnglishName</string>
                <com.tongji.hbase.migration.common.HTableDef_-ColumnInfo>
                  <columnName>brandEnglishName</columnName>
                  <columnType>STRING</columnType>
                  <refTable>Brand</refTable>
                  <refKey>brandEnglishName</refKey>
                  <outer-class reference="../../../../../.."/>
                </com.tongji.hbase.migration.common.HTableDef_-ColumnInfo>
              </entry>
              <entry>
                <string>brandCreateDate</string>
                <com.tongji.hbase.migration.common.HTableDef_-ColumnInfo>
                  <columnName>brandCreateDate</columnName>
                  <columnType>DATETIME</columnType>
                  <refTable>Brand</refTable>
                  <refKey>brandCreateDate</refKey>
                  <outer-class reference="../../../../../.."/>
                </com.tongji.hbase.migration.common.HTableDef_-ColumnInfo>
              </entry>
              <entry>
                <string>brandName</string>
                <com.tongji.hbase.migration.common.HTableDef_-ColumnInfo>
                  <columnName>brandName</columnName>
                  <columnType>STRING</columnType>
                  <refTable>Brand</refTable>
                  <refKey>brandName</refKey>
                  <outer-class reference="../../../../../.."/>
                </com.tongji.hbase.migration.common.HTableDef_-ColumnInfo>
              </entry>
              <entry>
                <string>brandDesc</string>
                <com.tongji.hbase.migration.common.HTableDef_-ColumnInfo>
                  <columnName>brandDesc</columnName>
                  <columnType>STRING</columnType>
                  <refTable>Brand</refTable>
                  <refKey>brandDesc</refKey>
                  <outer-class reference="../../../../../.."/>
                </com.tongji.hbase.migration.common.HTableDef_-ColumnInfo>
              </entry>
              <entry>
                <string>pictureID</string>
                <com.tongji.hbase.migration.common.HTableDef_-ColumnInfo>
                  <columnName>pictureID</columnName>
                  <columnType>INT</columnType>
                  <refTable>Brand</refTable>
                  <refKey>pictureID</refKey>
                  <outer-class reference="../../../../../.."/>
                </com.tongji.hbase.migration.common.HTableDef_-ColumnInfo>
              </entry>
            </map>
          </entry>
        </columnInfos>
      </com.tongji.hbase.migration.common.HTableDef>
    </entry>
    <entry>
      <string>Collection</string>
      <com.tongji.hbase.migration.common.HTableDef>
        <tableName>Collection</tableName>
        <rowKey>collectionID</rowKey>
        <columnInfos>
          <entry>
            <string>Collection</string>
            <map>
              <entry>
                <string>typeName</string>
                <com.tongji.hbase.migration.common.HTableDef_-ColumnInfo>
                  <columnName>typeName</columnName>
                  <columnType>STRING</columnType>
                  <refTable>Collection</refTable>
                  <refKey>typeName</refKey>
                  <outer-class reference="../../../../../.."/>
                </com.tongji.hbase.migration.common.HTableDef_-ColumnInfo>
              </entry>
              <entry>
                <string>userID</string>
                <com.tongji.hbase.migration.common.HTableDef_-ColumnInfo>
                  <columnName>userID</columnName>
                  <columnType>INT</columnType>
                  <refTable>Collection</refTable>
                  <refKey>userID</refKey>
                  <outer-class reference="../../../../../.."/>
                </com.tongji.hbase.migration.common.HTableDef_-ColumnInfo>
              </entry>
              <entry>
                <string>collectionID</string>
                <com.tongji.hbase.migration.common.HTableDef_-ColumnInfo>
                  <columnName>collectionID</columnName>
                  <columnType>INT</columnType>
                  <refTable>Collection</refTable>
                  <refKey>collectionID</refKey>
                  <outer-class reference="../../../../../.."/>
                </com.tongji.hbase.migration.common.HTableDef_-ColumnInfo>
              </entry>
              <entry>
                <string>goodsIDS</string>
                <com.tongji.hbase.migration.common.HTableDef_-ColumnInfo>
                  <columnName>goodsIDS</columnName>
                  <columnType>STRING</columnType>
                  <refTable>Collection</refTable>
                  <refKey>goodsIDS</refKey>
                  <outer-class reference="../../../../../.."/>
                </com.tongji.hbase.migration.common.HTableDef_-ColumnInfo>
              </entry>
              <entry>
                <string>type</string>
                <com.tongji.hbase.migration.common.HTableDef_-ColumnInfo>
                  <columnName>type</columnName>
                  <columnType>STRING</columnType>
                  <refTable>Collection</refTable>
                  <refKey>type</refKey>
                  <outer-class reference="../../../../../.."/>
                </com.tongji.hbase.migration.common.HTableDef_-ColumnInfo>
              </entry>
            </map>
          </entry>
        </columnInfos>
      </com.tongji.hbase.migration.common.HTableDef>
    </entry>
    <entry>
      <string>Type</string>
      <com.tongji.hbase.migration.common.HTableDef>
        <tableName>Type</tableName>
        <rowKey>typeID</rowKey>
        <columnInfos>
          <entry>
            <string>Type</string>
            <map>
              <entry>
                <string>typeName</string>
                <com.tongji.hbase.migration.common.HTableDef_-ColumnInfo>
                  <columnName>typeName</columnName>
                  <columnType>STRING</columnType>
                  <refTable>Type</refTable>
                  <refKey>typeName</refKey>
                  <outer-class reference="../../../../../.."/>
                </com.tongji.hbase.migration.common.HTableDef_-ColumnInfo>
              </entry>
              <entry>
                <string>parentID</string>
                <com.tongji.hbase.migration.common.HTableDef_-ColumnInfo>
                  <columnName>parentID</columnName>
                  <columnType>INT</columnType>
                  <refTable>Type</refTable>
                  <refKey>parentID</refKey>
                  <outer-class reference="../../../../../.."/>
                </com.tongji.hbase.migration.common.HTableDef_-ColumnInfo>
              </entry>
              <entry>
                <string>tag</string>
                <com.tongji.hbase.migration.common.HTableDef_-ColumnInfo>
                  <columnName>tag</columnName>
                  <columnType>STRING</columnType>
                  <refTable>Type</refTable>
                  <refKey>tag</refKey>
                  <outer-class reference="../../../../../.."/>
                </com.tongji.hbase.migration.common.HTableDef_-ColumnInfo>
              </entry>
              <entry>
                <string>typeLevel</string>
                <com.tongji.hbase.migration.common.HTableDef_-ColumnInfo>
                  <columnName>typeLevel</columnName>
                  <columnType>INT</columnType>
                  <refTable>Type</refTable>
                  <refKey>typeLevel</refKey>
                  <outer-class reference="../../../../../.."/>
                </com.tongji.hbase.migration.common.HTableDef_-ColumnInfo>
              </entry>
              <entry>
                <string>typeCreateDate</string>
                <com.tongji.hbase.migration.common.HTableDef_-ColumnInfo>
                  <columnName>typeCreateDate</columnName>
                  <columnType>DATETIME</columnType>
                  <refTable>Type</refTable>
                  <refKey>typeCreateDate</refKey>
                  <outer-class reference="../../../../../.."/>
                </com.tongji.hbase.migration.common.HTableDef_-ColumnInfo>
              </entry>
              <entry>
                <string>typeID</string>
                <com.tongji.hbase.migration.common.HTableDef_-ColumnInfo>
                  <columnName>typeID</columnName>
                  <columnType>INT</columnType>
                  <refTable>Type</refTable>
                  <refKey>typeID</refKey>
                  <outer-class reference="../../../../../.."/>
                </com.tongji.hbase.migration.common.HTableDef_-ColumnInfo>
              </entry>
              <entry>
                <string>typeCreator</string>
                <com.tongji.hbase.migration.common.HTableDef_-ColumnInfo>
                  <columnName>typeCreator</columnName>
                  <columnType>STRING</columnType>
                  <refTable>Type</refTable>
                  <refKey>typeCreator</refKey>
                  <outer-class reference="../../../../../.."/>
                </com.tongji.hbase.migration.common.HTableDef_-ColumnInfo>
              </entry>
            </map>
          </entry>
        </columnInfos>
      </com.tongji.hbase.migration.common.HTableDef>
    </entry>
    <entry>
      <string>House</string>
      <com.tongji.hbase.migration.common.HTableDef>
        <tableName>House</tableName>
        <rowKey>houseID</rowKey>
        <columnInfos>
          <entry>
            <string>House</string>
            <map>
              <entry>
                <string>houseModelSrc</string>
                <com.tongji.hbase.migration.common.HTableDef_-ColumnInfo>
                  <columnName>houseModelSrc</columnName>
                  <columnType>STRING</columnType>
                  <refTable>House</refTable>
                  <refKey>houseModelSrc</refKey>
                  <outer-class reference="../../../../../.."/>
                </com.tongji.hbase.migration.common.HTableDef_-ColumnInfo>
              </entry>
              <entry>
                <string>houseArea</string>
                <com.tongji.hbase.migration.common.HTableDef_-ColumnInfo>
                  <columnName>houseArea</columnName>
                  <columnType>DOUBLE</columnType>
                  <refTable>House</refTable>
                  <refKey>houseArea</refKey>
                  <outer-class reference="../../../../../.."/>
                </com.tongji.hbase.migration.common.HTableDef_-ColumnInfo>
              </entry>
              <entry>
                <string>tag</string>
                <com.tongji.hbase.migration.common.HTableDef_-ColumnInfo>
                  <columnName>tag</columnName>
                  <columnType>INT</columnType>
                  <refTable>House</refTable>
                  <refKey>tag</refKey>
                  <outer-class reference="../../../../../.."/>
                </com.tongji.hbase.migration.common.HTableDef_-ColumnInfo>
              </entry>
              <entry>
                <string>houseRemark</string>
                <com.tongji.hbase.migration.common.HTableDef_-ColumnInfo>
                  <columnName>houseRemark</columnName>
                  <columnType>STRING</columnType>
                  <refTable>House</refTable>
                  <refKey>houseRemark</refKey>
                  <outer-class reference="../../../../../.."/>
                </com.tongji.hbase.migration.common.HTableDef_-ColumnInfo>
              </entry>
              <entry>
                <string>cantavilID</string>
                <com.tongji.hbase.migration.common.HTableDef_-ColumnInfo>
                  <columnName>cantavilID</columnName>
                  <columnType>INT</columnType>
                  <refTable>House</refTable>
                  <refKey>cantavilID</refKey>
                  <outer-class reference="../../../../../.."/>
                </com.tongji.hbase.migration.common.HTableDef_-ColumnInfo>
              </entry>
              <entry>
                <string>housePicSrc</string>
                <com.tongji.hbase.migration.common.HTableDef_-ColumnInfo>
                  <columnName>housePicSrc</columnName>
                  <columnType>STRING</columnType>
                  <refTable>House</refTable>
                  <refKey>housePicSrc</refKey>
                  <outer-class reference="../../../../../.."/>
                </com.tongji.hbase.migration.common.HTableDef_-ColumnInfo>
              </entry>
              <entry>
                <string>houseName</string>
                <com.tongji.hbase.migration.common.HTableDef_-ColumnInfo>
                  <columnName>houseName</columnName>
                  <columnType>STRING</columnType>
                  <refTable>House</refTable>
                  <refKey>houseName</refKey>
                  <outer-class reference="../../../../../.."/>
                </com.tongji.hbase.migration.common.HTableDef_-ColumnInfo>
              </entry>
              <entry>
                <string>houseCreator</string>
                <com.tongji.hbase.migration.common.HTableDef_-ColumnInfo>
                  <columnName>houseCreator</columnName>
                  <columnType>STRING</columnType>
                  <refTable>House</refTable>
                  <refKey>houseCreator</refKey>
                  <outer-class reference="../../../../../.."/>
                </com.tongji.hbase.migration.common.HTableDef_-ColumnInfo>
              </entry>
              <entry>
                <string>houseTypeID</string>
                <com.tongji.hbase.migration.common.HTableDef_-ColumnInfo>
                  <columnName>houseTypeID</columnName>
                  <columnType>INT</columnType>
                  <refTable>House</refTable>
                  <refKey>houseTypeID</refKey>
                  <outer-class reference="../../../../../.."/>
                </com.tongji.hbase.migration.common.HTableDef_-ColumnInfo>
              </entry>
              <entry>
                <string>houseFormID</string>
                <com.tongji.hbase.migration.common.HTableDef_-ColumnInfo>
                  <columnName>houseFormID</columnName>
                  <columnType>INT</columnType>
                  <refTable>House</refTable>
                  <refKey>houseFormID</refKey>
                  <outer-class reference="../../../../../.."/>
                </com.tongji.hbase.migration.common.HTableDef_-ColumnInfo>
              </entry>
              <entry>
                <string>houseID</string>
                <com.tongji.hbase.migration.common.HTableDef_-ColumnInfo>
                  <columnName>houseID</columnName>
                  <columnType>INT</columnType>
                  <refTable>House</refTable>
                  <refKey>houseID</refKey>
                  <outer-class reference="../../../../../.."/>
                </com.tongji.hbase.migration.common.HTableDef_-ColumnInfo>
              </entry>
              <entry>
                <string>houseCreateDate</string>
                <com.tongji.hbase.migration.common.HTableDef_-ColumnInfo>
                  <columnName>houseCreateDate</columnName>
                  <columnType>DATETIME</columnType>
                  <refTable>House</refTable>
                  <refKey>houseCreateDate</refKey>
                  <outer-class reference="../../../../../.."/>
                </com.tongji.hbase.migration.common.HTableDef_-ColumnInfo>
              </entry>
              <entry>
                <string>houseStyleIDs</string>
                <com.tongji.hbase.migration.common.HTableDef_-ColumnInfo>
                  <columnName>houseStyleIDs</columnName>
                  <columnType>STRING</columnType>
                  <refTable>House</refTable>
                  <refKey>houseStyleIDs</refKey>
                  <outer-class reference="../../../../../.."/>
                </com.tongji.hbase.migration.common.HTableDef_-ColumnInfo>
              </entry>
              <entry>
                <string>designerID</string>
                <com.tongji.hbase.migration.common.HTableDef_-ColumnInfo>
                  <columnName>designerID</columnName>
                  <columnType>INT</columnType>
                  <refTable>House</refTable>
                  <refKey>designerID</refKey>
                  <outer-class reference="../../../../../.."/>
                </com.tongji.hbase.migration.common.HTableDef_-ColumnInfo>
              </entry>
            </map>
          </entry>
        </columnInfos>
      </com.tongji.hbase.migration.common.HTableDef>
    </entry>
    <entry>
      <string>Goods</string>
      <com.tongji.hbase.migration.common.HTableDef>
        <tableName>Goods</tableName>
        <rowKey>goodsID</rowKey>
        <columnInfos>
          <entry>
            <string>Picture</string>
            <map>
              <entry>
                <string>pictureSrc</string>
                <com.tongji.hbase.migration.common.HTableDef_-ColumnInfo>
                  <columnName>pictureSrc</columnName>
                  <columnType>STRING</columnType>
                  <refTable>Picture</refTable>
                  <refKey>pictureSrc</refKey>
                  <outer-class reference="../../../../../.."/>
                </com.tongji.hbase.migration.common.HTableDef_-ColumnInfo>
              </entry>
              <entry>
                <string>pictureType</string>
                <com.tongji.hbase.migration.common.HTableDef_-ColumnInfo>
                  <columnName>pictureType</columnName>
                  <columnType>STRING</columnType>
                  <refTable>Picture</refTable>
                  <refKey>pictureType</refKey>
                  <outer-class reference="../../../../../.."/>
                </com.tongji.hbase.migration.common.HTableDef_-ColumnInfo>
              </entry>
              <entry>
                <string>picCreator</string>
                <com.tongji.hbase.migration.common.HTableDef_-ColumnInfo>
                  <columnName>picCreator</columnName>
                  <columnType>STRING</columnType>
                  <refTable>Picture</refTable>
                  <refKey>picCreator</refKey>
                  <outer-class reference="../../../../../.."/>
                </com.tongji.hbase.migration.common.HTableDef_-ColumnInfo>
              </entry>
              <entry>
                <string>picCreateDate</string>
                <com.tongji.hbase.migration.common.HTableDef_-ColumnInfo>
                  <columnName>picCreateDate</columnName>
                  <columnType>DATETIME</columnType>
                  <refTable>Picture</refTable>
                  <refKey>picCreateDate</refKey>
                  <outer-class reference="../../../../../.."/>
                </com.tongji.hbase.migration.common.HTableDef_-ColumnInfo>
              </entry>
              <entry>
                <string>pictureID</string>
                <com.tongji.hbase.migration.common.HTableDef_-ColumnInfo>
                  <columnName>pictureID</columnName>
                  <columnType>INT</columnType>
                  <refTable>Picture</refTable>
                  <refKey>pictureID</refKey>
                  <outer-class reference="../../../../../.."/>
                </com.tongji.hbase.migration.common.HTableDef_-ColumnInfo>
              </entry>
              <entry>
                <string>typeID</string>
                <com.tongji.hbase.migration.common.HTableDef_-ColumnInfo>
                  <columnName>typeID</columnName>
                  <columnType>INT</columnType>
                  <refTable>Picture</refTable>
                  <refKey>typeID</refKey>
                  <outer-class reference="../../../../../.."/>
                </com.tongji.hbase.migration.common.HTableDef_-ColumnInfo>
              </entry>
            </map>
          </entry>
          <entry>
            <string>Model</string>
            <map>
              <entry>
                <string>packageWeight</string>
                <com.tongji.hbase.migration.common.HTableDef_-ColumnInfo>
                  <columnName>packageWeight</columnName>
                  <columnType>DOUBLE</columnType>
                  <refTable>Model</refTable>
                  <refKey>packageWeight</refKey>
                  <outer-class reference="../../../../../.."/>
                </com.tongji.hbase.migration.common.HTableDef_-ColumnInfo>
              </entry>
              <entry>
                <string>modelID</string>
                <com.tongji.hbase.migration.common.HTableDef_-ColumnInfo>
                  <columnName>modelID</columnName>
                  <columnType>INT</columnType>
                  <refTable>Model</refTable>
                  <refKey>modelID</refKey>
                  <outer-class reference="../../../../../.."/>
                </com.tongji.hbase.migration.common.HTableDef_-ColumnInfo>
              </entry>
              <entry>
                <string>height</string>
                <com.tongji.hbase.migration.common.HTableDef_-ColumnInfo>
                  <columnName>height</columnName>
                  <columnType>DOUBLE</columnType>
                  <refTable>Model</refTable>
                  <refKey>height</refKey>
                  <outer-class reference="../../../../../.."/>
                </com.tongji.hbase.migration.common.HTableDef_-ColumnInfo>
              </entry>
              <entry>
                <string>isDefault</string>
                <com.tongji.hbase.migration.common.HTableDef_-ColumnInfo>
                  <columnName>isDefault</columnName>
                  <columnType>BOOLEAN</columnType>
                  <refTable>Model</refTable>
                  <refKey>isDefault</refKey>
                  <outer-class reference="../../../../../.."/>
                </com.tongji.hbase.migration.common.HTableDef_-ColumnInfo>
              </entry>
              <entry>
                <string>width</string>
                <com.tongji.hbase.migration.common.HTableDef_-ColumnInfo>
                  <columnName>width</columnName>
                  <columnType>DOUBLE</columnType>
                  <refTable>Model</refTable>
                  <refKey>width</refKey>
                  <outer-class reference="../../../../../.."/>
                </com.tongji.hbase.migration.common.HTableDef_-ColumnInfo>
              </entry>
              <entry>
                <string>modelSrc</string>
                <com.tongji.hbase.migration.common.HTableDef_-ColumnInfo>
                  <columnName>modelSrc</columnName>
                  <columnType>STRING</columnType>
                  <refTable>Model</refTable>
                  <refKey>modelSrc</refKey>
                  <outer-class reference="../../../../../.."/>
                </com.tongji.hbase.migration.common.HTableDef_-ColumnInfo>
              </entry>
              <entry>
                <string>length</string>
                <com.tongji.hbase.migration.common.HTableDef_-ColumnInfo>
                  <columnName>length</columnName>
                  <columnType>DOUBLE</columnType>
                  <refTable>Model</refTable>
                  <refKey>length</refKey>
                  <outer-class reference="../../../../../.."/>
                </com.tongji.hbase.migration.common.HTableDef_-ColumnInfo>
              </entry>
              <entry>
                <string>modelCreator</string>
                <com.tongji.hbase.migration.common.HTableDef_-ColumnInfo>
                  <columnName>modelCreator</columnName>
                  <columnType>STRING</columnType>
                  <refTable>Model</refTable>
                  <refKey>modelCreator</refKey>
                  <outer-class reference="../../../../../.."/>
                </com.tongji.hbase.migration.common.HTableDef_-ColumnInfo>
              </entry>
              <entry>
                <string>goodsID</string>
                <com.tongji.hbase.migration.common.HTableDef_-ColumnInfo>
                  <columnName>goodsID</columnName>
                  <columnType>INT</columnType>
                  <refTable>Model</refTable>
                  <refKey>goodsID</refKey>
                  <outer-class reference="../../../../../.."/>
                </com.tongji.hbase.migration.common.HTableDef_-ColumnInfo>
              </entry>
              <entry>
                <string>modelCreateDate</string>
                <com.tongji.hbase.migration.common.HTableDef_-ColumnInfo>
                  <columnName>modelCreateDate</columnName>
                  <columnType>DATETIME</columnType>
                  <refTable>Model</refTable>
                  <refKey>modelCreateDate</refKey>
                  <outer-class reference="../../../../../.."/>
                </com.tongji.hbase.migration.common.HTableDef_-ColumnInfo>
              </entry>
              <entry>
                <string>packageSize</string>
                <com.tongji.hbase.migration.common.HTableDef_-ColumnInfo>
                  <columnName>packageSize</columnName>
                  <columnType>STRING</columnType>
                  <refTable>Model</refTable>
                  <refKey>packageSize</refKey>
                  <outer-class reference="../../../../../.."/>
                </com.tongji.hbase.migration.common.HTableDef_-ColumnInfo>
              </entry>
            </map>
          </entry>
          <entry>
            <string>GoodsRelated</string>
            <map>
              <entry>
                <string>colorID</string>
                <com.tongji.hbase.migration.common.HTableDef_-ColumnInfo>
                  <columnName>colorID</columnName>
                  <columnType>INT</columnType>
                  <refTable>GoodsRelated</refTable>
                  <refKey>colorID</refKey>
                  <outer-class reference="../../../../../.."/>
                </com.tongji.hbase.migration.common.HTableDef_-ColumnInfo>
              </entry>
              <entry>
                <string>goodsRelatedID</string>
                <com.tongji.hbase.migration.common.HTableDef_-ColumnInfo>
                  <columnName>goodsRelatedID</columnName>
                  <columnType>INT</columnType>
                  <refTable>GoodsRelated</refTable>
                  <refKey>goodsRelatedID</refKey>
                  <outer-class reference="../../../../../.."/>
                </com.tongji.hbase.migration.common.HTableDef_-ColumnInfo>
              </entry>
              <entry>
                <string>modelID</string>
                <com.tongji.hbase.migration.common.HTableDef_-ColumnInfo>
                  <columnName>modelID</columnName>
                  <columnType>INT</columnType>
                  <refTable>GoodsRelated</refTable>
                  <refKey>modelID</refKey>
                  <outer-class reference="../../../../../.."/>
                </com.tongji.hbase.migration.common.HTableDef_-ColumnInfo>
              </entry>
              <entry>
                <string>goodsRelatedCreateDate</string>
                <com.tongji.hbase.migration.common.HTableDef_-ColumnInfo>
                  <columnName>goodsRelatedCreateDate</columnName>
                  <columnType>DATETIME</columnType>
                  <refTable>GoodsRelated</refTable>
                  <refKey>goodsRelatedCreateDate</refKey>
                  <outer-class reference="../../../../../.."/>
                </com.tongji.hbase.migration.common.HTableDef_-ColumnInfo>
              </entry>
              <entry>
                <string>goodsRelatedCreator</string>
                <com.tongji.hbase.migration.common.HTableDef_-ColumnInfo>
                  <columnName>goodsRelatedCreator</columnName>
                  <columnType>STRING</columnType>
                  <refTable>GoodsRelated</refTable>
                  <refKey>goodsRelatedCreator</refKey>
                  <outer-class reference="../../../../../.."/>
                </com.tongji.hbase.migration.common.HTableDef_-ColumnInfo>
              </entry>
              <entry>
                <string>goodsPrice</string>
                <com.tongji.hbase.migration.common.HTableDef_-ColumnInfo>
                  <columnName>goodsPrice</columnName>
                  <columnType>DOUBLE</columnType>
                  <refTable>GoodsRelated</refTable>
                  <refKey>goodsPrice</refKey>
                  <outer-class reference="../../../../../.."/>
                </com.tongji.hbase.migration.common.HTableDef_-ColumnInfo>
              </entry>
              <entry>
                <string>goodsCount</string>
                <com.tongji.hbase.migration.common.HTableDef_-ColumnInfo>
                  <columnName>goodsCount</columnName>
                  <columnType>INT</columnType>
                  <refTable>GoodsRelated</refTable>
                  <refKey>goodsCount</refKey>
                  <outer-class reference="../../../../../.."/>
                </com.tongji.hbase.migration.common.HTableDef_-ColumnInfo>
              </entry>
              <entry>
                <string>pictureID</string>
                <com.tongji.hbase.migration.common.HTableDef_-ColumnInfo>
                  <columnName>pictureID</columnName>
                  <columnType>INT</columnType>
                  <refTable>GoodsRelated</refTable>
                  <refKey>pictureID</refKey>
                  <outer-class reference="../../../../../.."/>
                </com.tongji.hbase.migration.common.HTableDef_-ColumnInfo>
              </entry>
            </map>
          </entry>
          <entry>
            <string>Goods</string>
            <map>
              <entry>
                <string>goodsStyle</string>
                <com.tongji.hbase.migration.common.HTableDef_-ColumnInfo>
                  <columnName>goodsStyle</columnName>
                  <columnType>STRING</columnType>
                  <refTable>Goods</refTable>
                  <refKey>goodsStyle</refKey>
                  <outer-class reference="../../../../../.."/>
                </com.tongji.hbase.migration.common.HTableDef_-ColumnInfo>
              </entry>
              <entry>
                <string>goodsCreator</string>
                <com.tongji.hbase.migration.common.HTableDef_-ColumnInfo>
                  <columnName>goodsCreator</columnName>
                  <columnType>STRING</columnType>
                  <refTable>Goods</refTable>
                  <refKey>goodsCreator</refKey>
                  <outer-class reference="../../../../../.."/>
                </com.tongji.hbase.migration.common.HTableDef_-ColumnInfo>
              </entry>
              <entry>
                <string>goodsPackage</string>
                <com.tongji.hbase.migration.common.HTableDef_-ColumnInfo>
                  <columnName>goodsPackage</columnName>
                  <columnType>STRING</columnType>
                  <refTable>Goods</refTable>
                  <refKey>goodsPackage</refKey>
                  <outer-class reference="../../../../../.."/>
                </com.tongji.hbase.migration.common.HTableDef_-ColumnInfo>
              </entry>
              <entry>
                <string>packageCount</string>
                <com.tongji.hbase.migration.common.HTableDef_-ColumnInfo>
                  <columnName>packageCount</columnName>
                  <columnType>INT</columnType>
                  <refTable>Goods</refTable>
                  <refKey>packageCount</refKey>
                  <outer-class reference="../../../../../.."/>
                </com.tongji.hbase.migration.common.HTableDef_-ColumnInfo>
              </entry>
              <entry>
                <string>goodsLocation</string>
                <com.tongji.hbase.migration.common.HTableDef_-ColumnInfo>
                  <columnName>goodsLocation</columnName>
                  <columnType>STRING</columnType>
                  <refTable>Goods</refTable>
                  <refKey>goodsLocation</refKey>
                  <outer-class reference="../../../../../.."/>
                </com.tongji.hbase.migration.common.HTableDef_-ColumnInfo>
              </entry>
              <entry>
                <string>pictureIDs</string>
                <com.tongji.hbase.migration.common.HTableDef_-ColumnInfo>
                  <columnName>pictureIDs</columnName>
                  <columnType>STRING</columnType>
                  <refTable>Goods</refTable>
                  <refKey>pictureIDs</refKey>
                  <outer-class reference="../../../../../.."/>
                </com.tongji.hbase.migration.common.HTableDef_-ColumnInfo>
              </entry>
              <entry>
                <string>goodsMaterial</string>
                <com.tongji.hbase.migration.common.HTableDef_-ColumnInfo>
                  <columnName>goodsMaterial</columnName>
                  <columnType>STRING</columnType>
                  <refTable>Goods</refTable>
                  <refKey>goodsMaterial</refKey>
                  <outer-class reference="../../../../../.."/>
                </com.tongji.hbase.migration.common.HTableDef_-ColumnInfo>
              </entry>
              <entry>
                <string>brandID</string>
                <com.tongji.hbase.migration.common.HTableDef_-ColumnInfo>
                  <columnName>brandID</columnName>
                  <columnType>INT</columnType>
                  <refTable>Goods</refTable>
                  <refKey>brandID</refKey>
                  <outer-class reference="../../../../../.."/>
                </com.tongji.hbase.migration.common.HTableDef_-ColumnInfo>
              </entry>
              <entry>
                <string>goodsBill</string>
                <com.tongji.hbase.migration.common.HTableDef_-ColumnInfo>
                  <columnName>goodsBill</columnName>
                  <columnType>INT</columnType>
                  <refTable>Goods</refTable>
                  <refKey>goodsBill</refKey>
                  <outer-class reference="../../../../../.."/>
                </com.tongji.hbase.migration.common.HTableDef_-ColumnInfo>
              </entry>
              <entry>
                <string>goodsGuaranteePeriod</string>
                <com.tongji.hbase.migration.common.HTableDef_-ColumnInfo>
                  <columnName>goodsGuaranteePeriod</columnName>
                  <columnType>DOUBLE</columnType>
                  <refTable>Goods</refTable>
                  <refKey>goodsGuaranteePeriod</refKey>
                  <outer-class reference="../../../../../.."/>
                </com.tongji.hbase.migration.common.HTableDef_-ColumnInfo>
              </entry>
              <entry>
                <string>goodsCreateDate</string>
                <com.tongji.hbase.migration.common.HTableDef_-ColumnInfo>
                  <columnName>goodsCreateDate</columnName>
                  <columnType>DATETIME</columnType>
                  <refTable>Goods</refTable>
                  <refKey>goodsCreateDate</refKey>
                  <outer-class reference="../../../../../.."/>
                </com.tongji.hbase.migration.common.HTableDef_-ColumnInfo>
              </entry>
              <entry>
                <string>goodsInstallCost</string>
                <com.tongji.hbase.migration.common.HTableDef_-ColumnInfo>
                  <columnName>goodsInstallCost</columnName>
                  <columnType>DOUBLE</columnType>
                  <refTable>Goods</refTable>
                  <refKey>goodsInstallCost</refKey>
                  <outer-class reference="../../../../../.."/>
                </com.tongji.hbase.migration.common.HTableDef_-ColumnInfo>
              </entry>
              <entry>
                <string>goodsID</string>
                <com.tongji.hbase.migration.common.HTableDef_-ColumnInfo>
                  <columnName>goodsID</columnName>
                  <columnType>INT</columnType>
                  <refTable>Goods</refTable>
                  <refKey>goodsID</refKey>
                  <outer-class reference="../../../../../.."/>
                </com.tongji.hbase.migration.common.HTableDef_-ColumnInfo>
              </entry>
              <entry>
                <string>goodsUnit</string>
                <com.tongji.hbase.migration.common.HTableDef_-ColumnInfo>
                  <columnName>goodsUnit</columnName>
                  <columnType>STRING</columnType>
                  <refTable>Goods</refTable>
                  <refKey>goodsUnit</refKey>
                  <outer-class reference="../../../../../.."/>
                </com.tongji.hbase.migration.common.HTableDef_-ColumnInfo>
              </entry>
              <entry>
                <string>goodsName</string>
                <com.tongji.hbase.migration.common.HTableDef_-ColumnInfo>
                  <columnName>goodsName</columnName>
                  <columnType>STRING</columnType>
                  <refTable>Goods</refTable>
                  <refKey>goodsName</refKey>
                  <outer-class reference="../../../../../.."/>
                </com.tongji.hbase.migration.common.HTableDef_-ColumnInfo>
              </entry>
              <entry>
                <string>goodsCityService</string>
                <com.tongji.hbase.migration.common.HTableDef_-ColumnInfo>
                  <columnName>goodsCityService</columnName>
                  <columnType>STRING</columnType>
                  <refTable>Goods</refTable>
                  <refKey>goodsCityService</refKey>
                  <outer-class reference="../../../../../.."/>
                </com.tongji.hbase.migration.common.HTableDef_-ColumnInfo>
              </entry>
              <entry>
                <string>goodsType</string>
                <com.tongji.hbase.migration.common.HTableDef_-ColumnInfo>
                  <columnName>goodsType</columnName>
                  <columnType>STRING</columnType>
                  <refTable>Goods</refTable>
                  <refKey>goodsType</refKey>
                  <outer-class reference="../../../../../.."/>
                </com.tongji.hbase.migration.common.HTableDef_-ColumnInfo>
              </entry>
              <entry>
                <string>typeID</string>
                <com.tongji.hbase.migration.common.HTableDef_-ColumnInfo>
                  <columnName>typeID</columnName>
                  <columnType>INT</columnType>
                  <refTable>Goods</refTable>
                  <refKey>typeID</refKey>
                  <outer-class reference="../../../../../.."/>
                </com.tongji.hbase.migration.common.HTableDef_-ColumnInfo>
              </entry>
            </map>
          </entry>
          <entry>
            <string>Color</string>
            <map>
              <entry>
                <string>colorID</string>
                <com.tongji.hbase.migration.common.HTableDef_-ColumnInfo>
                  <columnName>colorID</columnName>
                  <columnType>INT</columnType>
                  <refTable>Color</refTable>
                  <refKey>colorID</refKey>
                  <outer-class reference="../../../../../.."/>
                </com.tongji.hbase.migration.common.HTableDef_-ColumnInfo>
              </entry>
              <entry>
                <string>colorName</string>
                <com.tongji.hbase.migration.common.HTableDef_-ColumnInfo>
                  <columnName>colorName</columnName>
                  <columnType>STRING</columnType>
                  <refTable>Color</refTable>
                  <refKey>colorName</refKey>
                  <outer-class reference="../../../../../.."/>
                </com.tongji.hbase.migration.common.HTableDef_-ColumnInfo>
              </entry>
              <entry>
                <string>isDefault</string>
                <com.tongji.hbase.migration.common.HTableDef_-ColumnInfo>
                  <columnName>isDefault</columnName>
                  <columnType>BOOLEAN</columnType>
                  <refTable>Color</refTable>
                  <refKey>isDefault</refKey>
                  <outer-class reference="../../../../../.."/>
                </com.tongji.hbase.migration.common.HTableDef_-ColumnInfo>
              </entry>
              <entry>
                <string>goodsID</string>
                <com.tongji.hbase.migration.common.HTableDef_-ColumnInfo>
                  <columnName>goodsID</columnName>
                  <columnType>INT</columnType>
                  <refTable>Color</refTable>
                  <refKey>goodsID</refKey>
                  <outer-class reference="../../../../../.."/>
                </com.tongji.hbase.migration.common.HTableDef_-ColumnInfo>
              </entry>
              <entry>
                <string>colorNum</string>
                <com.tongji.hbase.migration.common.HTableDef_-ColumnInfo>
                  <columnName>colorNum</columnName>
                  <columnType>STRING</columnType>
                  <refTable>Color</refTable>
                  <refKey>colorNum</refKey>
                  <outer-class reference="../../../../../.."/>
                </com.tongji.hbase.migration.common.HTableDef_-ColumnInfo>
              </entry>
              <entry>
                <string>colorCreator</string>
                <com.tongji.hbase.migration.common.HTableDef_-ColumnInfo>
                  <columnName>colorCreator</columnName>
                  <columnType>STRING</columnType>
                  <refTable>Color</refTable>
                  <refKey>colorCreator</refKey>
                  <outer-class reference="../../../../../.."/>
                </com.tongji.hbase.migration.common.HTableDef_-ColumnInfo>
              </entry>
              <entry>
                <string>colorCreateDate</string>
                <com.tongji.hbase.migration.common.HTableDef_-ColumnInfo>
                  <columnName>colorCreateDate</columnName>
                  <columnType>DATETIME</columnType>
                  <refTable>Color</refTable>
                  <refKey>colorCreateDate</refKey>
                  <outer-class reference="../../../../../.."/>
                </com.tongji.hbase.migration.common.HTableDef_-ColumnInfo>
              </entry>
            </map>
          </entry>
        </columnInfos>
      </com.tongji.hbase.migration.common.HTableDef>
    </entry>
    <entry>
      <string>Cantavil</string>
      <com.tongji.hbase.migration.common.HTableDef>
        <tableName>Cantavil</tableName>
        <rowKey>cantavilID</rowKey>
        <columnInfos>
          <entry>
            <string>Picture</string>
            <map>
              <entry>
                <string>pictureSrc</string>
                <com.tongji.hbase.migration.common.HTableDef_-ColumnInfo>
                  <columnName>pictureSrc</columnName>
                  <columnType>STRING</columnType>
                  <refTable>Picture</refTable>
                  <refKey>pictureSrc</refKey>
                  <outer-class reference="../../../../../.."/>
                </com.tongji.hbase.migration.common.HTableDef_-ColumnInfo>
              </entry>
              <entry>
                <string>pictureType</string>
                <com.tongji.hbase.migration.common.HTableDef_-ColumnInfo>
                  <columnName>pictureType</columnName>
                  <columnType>STRING</columnType>
                  <refTable>Picture</refTable>
                  <refKey>pictureType</refKey>
                  <outer-class reference="../../../../../.."/>
                </com.tongji.hbase.migration.common.HTableDef_-ColumnInfo>
              </entry>
              <entry>
                <string>picCreator</string>
                <com.tongji.hbase.migration.common.HTableDef_-ColumnInfo>
                  <columnName>picCreator</columnName>
                  <columnType>STRING</columnType>
                  <refTable>Picture</refTable>
                  <refKey>picCreator</refKey>
                  <outer-class reference="../../../../../.."/>
                </com.tongji.hbase.migration.common.HTableDef_-ColumnInfo>
              </entry>
              <entry>
                <string>picCreateDate</string>
                <com.tongji.hbase.migration.common.HTableDef_-ColumnInfo>
                  <columnName>picCreateDate</columnName>
                  <columnType>DATETIME</columnType>
                  <refTable>Picture</refTable>
                  <refKey>picCreateDate</refKey>
                  <outer-class reference="../../../../../.."/>
                </com.tongji.hbase.migration.common.HTableDef_-ColumnInfo>
              </entry>
              <entry>
                <string>pictureID</string>
                <com.tongji.hbase.migration.common.HTableDef_-ColumnInfo>
                  <columnName>pictureID</columnName>
                  <columnType>INT</columnType>
                  <refTable>Picture</refTable>
                  <refKey>pictureID</refKey>
                  <outer-class reference="../../../../../.."/>
                </com.tongji.hbase.migration.common.HTableDef_-ColumnInfo>
              </entry>
              <entry>
                <string>typeID</string>
                <com.tongji.hbase.migration.common.HTableDef_-ColumnInfo>
                  <columnName>typeID</columnName>
                  <columnType>INT</columnType>
                  <refTable>Picture</refTable>
                  <refKey>typeID</refKey>
                  <outer-class reference="../../../../../.."/>
                </com.tongji.hbase.migration.common.HTableDef_-ColumnInfo>
              </entry>
            </map>
          </entry>
          <entry>
            <string>Cantavil</string>
            <map>
              <entry>
                <string>cantavilAddress</string>
                <com.tongji.hbase.migration.common.HTableDef_-ColumnInfo>
                  <columnName>cantavilAddress</columnName>
                  <columnType>STRING</columnType>
                  <refTable>Cantavil</refTable>
                  <refKey>cantavilAddress</refKey>
                  <outer-class reference="../../../../../.."/>
                </com.tongji.hbase.migration.common.HTableDef_-ColumnInfo>
              </entry>
              <entry>
                <string>cantavilRemark</string>
                <com.tongji.hbase.migration.common.HTableDef_-ColumnInfo>
                  <columnName>cantavilRemark</columnName>
                  <columnType>STRING</columnType>
                  <refTable>Cantavil</refTable>
                  <refKey>cantavilRemark</refKey>
                  <outer-class reference="../../../../../.."/>
                </com.tongji.hbase.migration.common.HTableDef_-ColumnInfo>
              </entry>
              <entry>
                <string>cantavilPic</string>
                <com.tongji.hbase.migration.common.HTableDef_-ColumnInfo>
                  <columnName>cantavilPic</columnName>
                  <columnType>STRING</columnType>
                  <refTable>Cantavil</refTable>
                  <refKey>cantavilPic</refKey>
                  <outer-class reference="../../../../../.."/>
                </com.tongji.hbase.migration.common.HTableDef_-ColumnInfo>
              </entry>
              <entry>
                <string>cantavilDeveloper</string>
                <com.tongji.hbase.migration.common.HTableDef_-ColumnInfo>
                  <columnName>cantavilDeveloper</columnName>
                  <columnType>STRING</columnType>
                  <refTable>Cantavil</refTable>
                  <refKey>cantavilDeveloper</refKey>
                  <outer-class reference="../../../../../.."/>
                </com.tongji.hbase.migration.common.HTableDef_-ColumnInfo>
              </entry>
              <entry>
                <string>cantavilName</string>
                <com.tongji.hbase.migration.common.HTableDef_-ColumnInfo>
                  <columnName>cantavilName</columnName>
                  <columnType>STRING</columnType>
                  <refTable>Cantavil</refTable>
                  <refKey>cantavilName</refKey>
                  <outer-class reference="../../../../../.."/>
                </com.tongji.hbase.migration.common.HTableDef_-ColumnInfo>
              </entry>
              <entry>
                <string>cantavilID</string>
                <com.tongji.hbase.migration.common.HTableDef_-ColumnInfo>
                  <columnName>cantavilID</columnName>
                  <columnType>INT</columnType>
                  <refTable>Cantavil</refTable>
                  <refKey>cantavilID</refKey>
                  <outer-class reference="../../../../../.."/>
                </com.tongji.hbase.migration.common.HTableDef_-ColumnInfo>
              </entry>
              <entry>
                <string>cantavilCreateDate</string>
                <com.tongji.hbase.migration.common.HTableDef_-ColumnInfo>
                  <columnName>cantavilCreateDate</columnName>
                  <columnType>DATETIME</columnType>
                  <refTable>Cantavil</refTable>
                  <refKey>cantavilCreateDate</refKey>
                  <outer-class reference="../../../../../.."/>
                </com.tongji.hbase.migration.common.HTableDef_-ColumnInfo>
              </entry>
              <entry>
                <string>cantavilCreator</string>
                <com.tongji.hbase.migration.common.HTableDef_-ColumnInfo>
                  <columnName>cantavilCreator</columnName>
                  <columnType>STRING</columnType>
                  <refTable>Cantavil</refTable>
                  <refKey>cantavilCreator</refKey>
                  <outer-class reference="../../../../../.."/>
                </com.tongji.hbase.migration.common.HTableDef_-ColumnInfo>
              </entry>
              <entry>
                <string>cantavilType</string>
                <com.tongji.hbase.migration.common.HTableDef_-ColumnInfo>
                  <columnName>cantavilType</columnName>
                  <columnType>STRING</columnType>
                  <refTable>Cantavil</refTable>
                  <refKey>cantavilType</refKey>
                  <outer-class reference="../../../../../.."/>
                </com.tongji.hbase.migration.common.HTableDef_-ColumnInfo>
              </entry>
              <entry>
                <string>developDesc</string>
                <com.tongji.hbase.migration.common.HTableDef_-ColumnInfo>
                  <columnName>developDesc</columnName>
                  <columnType>STRING</columnType>
                  <refTable>Cantavil</refTable>
                  <refKey>developDesc</refKey>
                  <outer-class reference="../../../../../.."/>
                </com.tongji.hbase.migration.common.HTableDef_-ColumnInfo>
              </entry>
              <entry>
                <string>pictureID</string>
                <com.tongji.hbase.migration.common.HTableDef_-ColumnInfo>
                  <columnName>pictureID</columnName>
                  <columnType>INT</columnType>
                  <refTable>Cantavil</refTable>
                  <refKey>pictureID</refKey>
                  <outer-class reference="../../../../../.."/>
                </com.tongji.hbase.migration.common.HTableDef_-ColumnInfo>
              </entry>
              <entry>
                <string>typeID</string>
                <com.tongji.hbase.migration.common.HTableDef_-ColumnInfo>
                  <columnName>typeID</columnName>
                  <columnType>INT</columnType>
                  <refTable>Cantavil</refTable>
                  <refKey>typeID</refKey>
                  <outer-class reference="../../../../../.."/>
                </com.tongji.hbase.migration.common.HTableDef_-ColumnInfo>
              </entry>
            </map>
          </entry>
        </columnInfos>
      </com.tongji.hbase.migration.common.HTableDef>
    </entry>
    <entry>
      <string>Design</string>
      <com.tongji.hbase.migration.common.HTableDef>
        <tableName>Design</tableName>
        <rowKey>designID</rowKey>
        <columnInfos>
          <entry>
            <string>Design</string>
            <map>
              <entry>
                <string>userID</string>
                <com.tongji.hbase.migration.common.HTableDef_-ColumnInfo>
                  <columnName>userID</columnName>
                  <columnType>INT</columnType>
                  <refTable>Design</refTable>
                  <refKey>userID</refKey>
                  <outer-class reference="../../../../../.."/>
                </com.tongji.hbase.migration.common.HTableDef_-ColumnInfo>
              </entry>
              <entry>
                <string>isReleased</string>
                <com.tongji.hbase.migration.common.HTableDef_-ColumnInfo>
                  <columnName>isReleased</columnName>
                  <columnType>BOOLEAN</columnType>
                  <refTable>Design</refTable>
                  <refKey>isReleased</refKey>
                  <outer-class reference="../../../../../.."/>
                </com.tongji.hbase.migration.common.HTableDef_-ColumnInfo>
              </entry>
              <entry>
                <string>designID</string>
                <com.tongji.hbase.migration.common.HTableDef_-ColumnInfo>
                  <columnName>designID</columnName>
                  <columnType>INT</columnType>
                  <refTable>Design</refTable>
                  <refKey>designID</refKey>
                  <outer-class reference="../../../../../.."/>
                </com.tongji.hbase.migration.common.HTableDef_-ColumnInfo>
              </entry>
              <entry>
                <string>designCreateDate</string>
                <com.tongji.hbase.migration.common.HTableDef_-ColumnInfo>
                  <columnName>designCreateDate</columnName>
                  <columnType>DATETIME</columnType>
                  <refTable>Design</refTable>
                  <refKey>designCreateDate</refKey>
                  <outer-class reference="../../../../../.."/>
                </com.tongji.hbase.migration.common.HTableDef_-ColumnInfo>
              </entry>
              <entry>
                <string>designPicSrc</string>
                <com.tongji.hbase.migration.common.HTableDef_-ColumnInfo>
                  <columnName>designPicSrc</columnName>
                  <columnType>STRING</columnType>
                  <refTable>Design</refTable>
                  <refKey>designPicSrc</refKey>
                  <outer-class reference="../../../../../.."/>
                </com.tongji.hbase.migration.common.HTableDef_-ColumnInfo>
              </entry>
              <entry>
                <string>designName</string>
                <com.tongji.hbase.migration.common.HTableDef_-ColumnInfo>
                  <columnName>designName</columnName>
                  <columnType>STRING</columnType>
                  <refTable>Design</refTable>
                  <refKey>designName</refKey>
                  <outer-class reference="../../../../../.."/>
                </com.tongji.hbase.migration.common.HTableDef_-ColumnInfo>
              </entry>
              <entry>
                <string>xmlSrc</string>
                <com.tongji.hbase.migration.common.HTableDef_-ColumnInfo>
                  <columnName>xmlSrc</columnName>
                  <columnType>STRING</columnType>
                  <refTable>Design</refTable>
                  <refKey>xmlSrc</refKey>
                  <outer-class reference="../../../../../.."/>
                </com.tongji.hbase.migration.common.HTableDef_-ColumnInfo>
              </entry>
            </map>
          </entry>
        </columnInfos>
      </com.tongji.hbase.migration.common.HTableDef>
    </entry>
  </htableDefs>
  <relationMappings enum-type="com.tongji.hbase.migration.Convertor$RelationType">
    <entry>
      <com.tongji.hbase.migration.Convertor_-RelationType>NEST</com.tongji.hbase.migration.Convertor_-RelationType>
      <map>
        <entry>
          <string>Goods</string>
          <set>
            <string>Model</string>
            <string>Color</string>
          </set>
        </entry>
      </map>
    </entry>
    <entry>
      <com.tongji.hbase.migration.Convertor_-RelationType>INLINE</com.tongji.hbase.migration.Convertor_-RelationType>
      <map>
        <entry>
          <string>Goods</string>
          <set>
            <string>GoodsRelated</string>
          </set>
        </entry>
      </map>
    </entry>
    <entry>
      <com.tongji.hbase.migration.Convertor_-RelationType>SPLIT</com.tongji.hbase.migration.Convertor_-RelationType>
      <map>
        <entry>
          <string>Brand</string>
          <set>
            <string>Picture</string>
          </set>
        </entry>
        <entry>
          <string>Goods</string>
          <set>
            <string>Picture</string>
          </set>
        </entry>
        <entry>
          <string>Cantavil</string>
          <set>
            <string>Picture</string>
          </set>
        </entry>
      </map>
    </entry>
  </relationMappings>
</com.tongji.hbase.migration.Adapter>